Metadata-Version: 2.4
Name: macapype
Version: 0.6
Summary: Pipeline for anatomic processing for macaque 
Author: Macatools team
Maintainer: Macapype developers
License: BSD-3-Clause
Requires-Python: >=3.10
License-File: LICENCE.txt
Requires-Dist: nipype
Requires-Dist: rdflib==6.3.1
Requires-Dist: pandas==2.2.3
Requires-Dist: matplotlib
Requires-Dist: nilearn
Requires-Dist: networkx
Requires-Dist: pybids
Requires-Dist: scikit-image
Requires-Dist: nibabel
Requires-Dist: numpy
Requires-Dist: SimpleITK
Provides-Extra: doc-deps
Requires-Dist: sphinx; extra == "doc-deps"
Requires-Dist: sphinx-gallery; extra == "doc-deps"
Requires-Dist: sphinx_bootstrap_theme; extra == "doc-deps"
Requires-Dist: numpydoc; extra == "doc-deps"
Requires-Dist: sphinxcontrib-fulltoc; extra == "doc-deps"
Provides-Extra: test-deps
Requires-Dist: pytest; extra == "test-deps"
Requires-Dist: pytest-cov; extra == "test-deps"
Requires-Dist: codecov; extra == "test-deps"
Provides-Extra: flake-deps
Requires-Dist: flake8; extra == "flake-deps"
Provides-Extra: test
Requires-Dist: macapype[flake_deps,test_deps]; extra == "test"
Provides-Extra: doc
Requires-Dist: macapype[doc_deps,flake_deps,test_deps]; extra == "doc"
Dynamic: license-file
